astra/__init__.py
astra/astra.py
astra/base/__init__.py
astra/base/pages.py
astra/connections/__init__.py
astra/connections/database.py
astra/connections/handler.py
astra/exceptions/__init__.py
astra/exceptions/db_exceptions.py
astra/generation/__init__.py
astra/generation/model.py
astra/groups/__init__.py
astra/groups/debug.py
astra/groups/jar.py
astra/groups/quote.py
astra_bot-1.3.4.dist-info/LICENSE
astra_bot-1.3.4.dist-info/METADATA
astra_bot-1.3.4.dist-info/WHEEL
astra_bot-1.3.4.dist-info/top_level.txt
astra_bot-1.3.4.dist-info/RECORD
