Metadata-Version: 2.1
Name: astra-bot
Version: 1.3.4
Summary: Discord bot capable of storing 'quotes' by users and simple construction of humorous sentences.
Author-email: Anokhi Suresh <anokhi.suresh@mail.mcgill.ca>
Project-URL: Homepage, https://github.com/anoaky/AstraSE
Project-URL: Issues, https://github.com/anoaky/AstraSE/issues
Classifier: Programming Language :: Python :: 3
Classifier: License :: OSI Approved :: MIT License
Classifier: Operating System :: OS Independent
Requires-Python: >=3.11
License-File: LICENSE
Requires-Dist: discord.py ==2.4.0
Requires-Dist: markovify ==0.9.4
Requires-Dist: valx ==0.2.0
Requires-Dist: numpy ==1.26.4
